TraceSpanTree/Log.py
TraceSpanTree/MultiNestDict.py
TraceSpanTree/SpanTree.py
TraceSpanTree/TraceGen.py
TraceSpanTree/__init__.py
tests/__init__.py
tests/test_demo1.py
tests/test_demo2.py
TraceSpanTree-1.0.0.dist-info/LICENSE
TraceSpanTree-1.0.0.dist-info/METADATA
TraceSpanTree-1.0.0.dist-info/WHEEL
TraceSpanTree-1.0.0.dist-info/top_level.txt
TraceSpanTree-1.0.0.dist-info/RECORD
