Metadata-Version: 2.1
Name: TraceSpanTree
Version: 1.0.0
Summary: A tool to assist QA Engineers in writing assertions by parsing program call traces.
Home-page: https://github.com/volmodaoist/SpanTree
Author: volmodaoist
Classifier: Programming Language :: Python :: 3
Classifier: License :: OSI Approved :: MIT License
Classifier: Operating System :: OS Independent
Requires-Python: >=3.6
License-File: LICENSE
